imlresearch/__init__.py
imlresearch/low_level/__init__.py
imlresearch/preprocessing_steps/__init__.py
imlresearch/researcher/__init__.py
imlresearch/src/version.py
imlresearch/src/data_handling/data_handler.py
imlresearch/src/data_handling/io/create_dataset.py
imlresearch/src/data_handling/io/decode_image.py
imlresearch/src/data_handling/io/save_images.py
imlresearch/src/data_handling/labelling/label_manager.py
imlresearch/src/data_handling/labelling/label_utils.py
imlresearch/src/data_handling/manipulation/pack_images_and_labels.py
imlresearch/src/data_handling/manipulation/prepare_dataset.py
imlresearch/src/data_handling/manipulation/shuffle_dataset.py
imlresearch/src/data_handling/manipulation/split_dataset.py
imlresearch/src/data_handling/manipulation/unpack_dataset.py
imlresearch/src/data_handling/tests/create_dataset_test.py
imlresearch/src/data_handling/tests/data_handler_test.py
imlresearch/src/data_handling/tests/label_manager_test.py
imlresearch/src/data_handling/tests/prepare_dataset_test.py
imlresearch/src/data_handling/tests/save_images_test.py
imlresearch/src/data_handling/tests/shuffle_dataset_test.py
imlresearch/src/data_handling/tests/split_dataset_test.py
imlresearch/src/data_handling/tests/test_runner.py
imlresearch/src/data_handling/tests/tfrecord_serialization_test.py
imlresearch/src/data_handling/tests/data/figure_4.png
imlresearch/src/data_handling/tests/data/figure_5.png
imlresearch/src/data_handling/tfrecord_serialization/deserialize.py
imlresearch/src/data_handling/tfrecord_serialization/serialize.py
imlresearch/src/experimenting/experiment.py
imlresearch/src/experimenting/helpers/ai_support.py
imlresearch/src/experimenting/helpers/create_experiment_report.py
imlresearch/src/experimenting/helpers/experiment_assets.py
imlresearch/src/experimenting/helpers/hparams_suggester.py
imlresearch/src/experimenting/helpers/last_score_singleton.py
imlresearch/src/experimenting/helpers/load_experiment_definition.py
imlresearch-0.1.0.dist-info/licenses/LICENSE
imlresearch-0.1.0.dist-info/METADATA
imlresearch-0.1.0.dist-info/WHEEL
imlresearch-0.1.0.dist-info/top_level.txt
imlresearch-0.1.0.dist-info/RECORD
