Metadata-Version: 2.4
Name: imlresearch
Version: 0.1.0
Summary: A Python Toolkit for Reproducible Image-Based ML Experiments
Author-email: SiulRek <luiskraker2000@gmail.com>
License: The MIT License (MIT)
Project-URL: Repository, https://github.com/SiulRek/ImageMLResearch
Project-URL: Documentation, https://imagemlresearch.readthedocs.io/en/api-development/
Classifier: Programming Language :: Python :: 3
Classifier: Programming Language :: Python :: 3.10
Classifier: Programming Language :: Python :: 3.11
Classifier: Programming Language :: Python :: 3.12
Classifier: Programming Language :: Python :: 3 :: Only
Classifier: License :: OSI Approved :: MIT License
Classifier: Operating System :: Unix
Classifier: Operating System :: Microsoft :: Windows
Classifier: Intended Audience :: Science/Research
Classifier: Topic :: Scientific/Engineering
Classifier: Topic :: Software Development
Requires-Python: >=3.10
License-File: LICENSE
Requires-Dist: tensorflow==2.17.0
Requires-Dist: pandas==2.2.2
Requires-Dist: matplotlib==3.8.0
Requires-Dist: openai==1.34.0
Requires-Dist: optuna==3.6.1
Requires-Dist: seaborn==0.13.2
Requires-Dist: scikit-learn==1.4.1.post1
Requires-Dist: opencv-python==4.8.1.78
Dynamic: license-file
